Workbook

Sheet Raw_Data
A1: Order_ID | B1: Date | C1: Region | D1: Sales_Rep | E1: Product_Category | F1: Product | G1: Units | H1: Unit_Price | I1: Discount | J1: Revenue | K1: Profit | L1: Month | M1: Quarter | N1: Profit_Margin
A2: 10001 | B2: 45472 | C2: Dubai | D2: Zain | E2: Retail Loans | F2: Personal Loan | G2: 6 | H2: 2542 | I2: 0.01 | J2: 15252 | K2: =J2*N2 -> 3050.4 | L2: 2024-06 | M2: Q2 | N2: =IF(Table_RawData[[#This Row],[Product_Category]]=$T$8,$U$8,IF(Table_RawData[[#This Row],[Product_Category]]=$T$9,$U$9,IF(Table_RawData[[#This Row],[Product_Category]]=$T$10,$U$10,IF(Table_RawData[[#This Row],[Product_Category]]=$T$11,$U$11,IF(Table_RawData[[#This Row],[Product_Category]]=$T$12,$U$12,"WRONG"))))) -> 0.2
A3: 10002 | B3: 45631 | C3: Dubai | D3: Karan | E3: Credit Cards | F3: Visa Classic | G3: 2 | H3: 18924 | I3: 0 | J3: 37848 | K3: =J3*N3 -> 11354.4 | L3: 2024-12 | M3: Q4 | N3: =IF(Table_RawData[[#This Row],[Product_Category]]=$T$8,$U$8,IF(Table_RawData[[#This Row],[Product_Category]]=$T$9,$U$9,IF(Table_RawData[[#This Row],[Product_Category]]=$T$10,$U$10,IF(Table_RawData[[#This Row],[Product_Category]]=$T$11,$U$11,IF(Table_RawData[[#This Row],[Product_Category]]=$T$12,$U$12,"WRONG"))))) -> 0.3
A4: 10003 | B4: 45338 | C4: Abu Dhabi | D4: Omar | E4: Deposits | F4: Savings Account | G4: 4 | H4: 27256 | I4: 0.02 | J4: 109024 | K4: =J4*N4 -> 10902.4 | L4: 2024-02 | M4: Q1 | N4: =IF(Table_RawData[[#This Row],[Product_Category]]=$T$8,$U$8,IF(Table_RawData[[#This Row],[Product_Category]]=$T$9,$U$9,IF(Table_RawData[[#This Row],[Product_Category]]=$T$10,$U$10,IF(Table_RawData[[#This Row],[Product_Category]]=$T$11,$U$11,IF(Table_RawData[[#This Row],[Product_Category]]=$T$12,$U$12,"WRONG"))))) -> 0.1
A5: 10004 | B5: 45463 | C5: Ras Al Khaimah | D5: Ravi | E5: SME Banking | F5: Trade Finance | G5: 6 | H5: 27790 | I5: 0.02 | J5: 166740 | K5: =J5*N5 -> 41685 | L5: 2024-06 | M5: Q2 | N5: =IF(Table_RawData[[#This Row],[Product_Category]]=$T$8,$U$8,IF(Table_RawData[[#This Row],[Product_Category]]=$T$9,$U$9,IF(Table_RawData[[#This Row],[Product_Category]]=$T$10,$U$10,IF(Table_RawData[[#This Row],[Product_Category]]=$T$11,$U$11,IF(Table_RawData[[#This Row],[Product_Category]]=$T$12,$U$12,"WRONG"))))) -> 0.25
A6: 10005 | B6: 45406 | C6: Ajman | D6: Ayesha | E6: Deposits | F6: Savings Account | G6: 4 | H6: 14116 | I6: 0.02 | J6: 56464 | K6: =J6*N6 -> 5646.4 | L6: 2024-04 | M6: Q2 | N6: =IF(Table_RawData[[#This Row],[Product_Category]]=$T$8,$U$8,IF(Table_RawData[[#This Row],[Product_Category]]=$T$9,$U$9,IF(Table_RawData[[#This Row],[Product_Category]]=$T$10,$U$10,IF(Table_RawData[[#This Row],[Product_Category]]=$T$11,$U$11,IF(Table_RawData[[#This Row],[Product_Category]]=$T$12,$U$12,"WRONG"))))) -> 0.1
A7: 10006 | B7: 45394 | C7: Ras Al Khaimah | D7: Priyanka | E7: Deposits | F7: Savings Account | G7: 1 | H7: 24960 | I7: 0.05 | J7: 24960 | K7: =J7*N7 -> 2496 | L7: 2024-04 | M7: Q2 | N7: =IF(Table_RawData[[#This Row],[Product_Category]]=$T$8,$U$8,IF(Table_RawData[[#This Row],[Product_Category]]=$T$9,$U$9,IF(Table_RawData[[#This Row],[Product_Category]]=$T$10,$U$10,IF(Table_RawData[[#This Row],[Product_Category]]=$T$11,$U$11,IF(Table_RawData[[#This Row],[Product_Category]]=$T$12,$U$12,"WRONG"))))) -> 0.1 | T7: Product Category | U7: Profit Margin
A8: 10007 | B8: 45353 | C8: Ajman | D8: Fatima | E8: Credit Cards | F8: Visa Classic | G8: 6 | H8: 28860 | I8: 0.02 | J8: 173160 | K8: =J8*N8 -> 51948 | L8: 2024-03 | M8: Q1 | N8: =IF(Table_RawData[[#This Row],[Product_Category]]=$T$8,$U$8,IF(Table_RawData[[#This Row],[Product_Category]]=$T$9,$U$9,IF(Table_RawData[[#This Row],[Product_Category]]=$T$10,$U$10,IF(Table_RawData[[#This Row],[Product_Category]]=$T$11,$U$11,IF(Table_RawData[[#This Row],[Product_Category]]=$T$12,$U$12,"WRONG"))))) -> 0.3 | T8: Retail Loans | U8: 0.2
A9: 10008 | B9: 45616 | C9: Sharjah | D9: Leena | E9: Wealth | F9: Bancassurance | G9: 9 | H9: 49529 | I9: 0.02 | J9: 445761 | K9: =J9*N9 -> 156016.35 | L9: 2024-11 | M9: Q4 | N9: =IF(Table_RawData[[#This Row],[Product_Category]]=$T$8,$U$8,IF(Table_RawData[[#This Row],[Product_Category]]=$T$9,$U$9,IF(Table_RawData[[#This Row],[Product_Category]]=$T$10,$U$10,IF(Table_RawData[[#This Row],[Product_Category]]=$T$11,$U$11,IF(Table_RawData[[#This Row],[Product_Category]]=$T$12,$U$12,"WRONG"))))) -> 0.35 | T9: Credit Cards | U9: 0.3
A10: 10009 | B10: 45419 | C10: Fujairah | D10: Omar | E10: Retail Loans | F10: Home Loan | G10: 3 | H10: 20087 | I10: 0.02 | J10: 60261 | K10: =J10*N10 -> 12052.2 | L10: 2024-05 | M10: Q2 | N10: =IF(Table_RawData[[#This Row],[Product_Category]]=$T$8,$U$8,IF(Table_RawData[[#This Row],[Product_Category]]=$T$9,$U$9,IF(Table_RawData[[#This Row],[Product_Category]]=$T$10,$U$10,IF(Table_RawData[[#This Row],[Product_Category]]=$T$11,$U$11,IF(Table_RawData[[#This Row],[Product_Category]]=$T$12,$U$12,"WRONG"))))) -> 0.2 | T10: Deposits | U10: 0.1
A11: 10010 | B11: 45379 | C11: Ras Al Khaimah | D11: Mohan | E11: Credit Cards | F11: Visa Gold | G11: 5 | H11: 30703 | I11: 0.01 | J11: 153515 | K11: =J11*N11 -> 46054.5 | L11: 2024-03 | M11: Q1 | N11: =IF(Table_RawData[[#This Row],[Product_Category]]=$T$8,$U$8,IF(Table_RawData[[#This Row],[Product_Category]]=$T$9,$U$9,IF(Table_RawData[[#This Row],[Product_Category]]=$T$10,$U$10,IF(Table_RawData[[#This Row],[Product_Category]]=$T$11,$U$11,IF(Table_RawData[[#This Row],[Product_Category]]=$T$12,$U$12,"WRONG"))))) -> 0.3 | T11: Wealth | U11: 0.35
A12: 10011 | B12: 45479 | C12: Ras Al Khaimah | D12: Fatima | E12: Credit Cards | F12: Visa Gold | G12: 9 | H12: 5835 | I12: 0.05 | J12: 52515 | K12: =J12*N12 -> 15754.5 | L12: 2024-07 | M12: Q3 | N12: =IF(Table_RawData[[#This Row],[Product_Category]]=$T$8,$U$8,IF(Table_RawData[[#This Row],[Product_Category]]=$T$9,$U$9,IF(Table_RawData[[#This Row],[Product_Category]]=$T$10,$U$10,IF(Table_RawData[[#This Row],[Product_Category]]=$T$11,$U$11,IF(Table_RawData[[#This Row],[Product_Category]]=$T$12,$U$12,"WRONG"))))) -> 0.3 | T12: SME Banking | U12: 0.25
A13: 10012 | B13: 45549 | C13: Abu Dhabi | D13: Fatima | E13: Retail Loans | F13: Home Loan | G13: 4 | H13: 36547 | I13: 0.05 | J13: 146188 | K13: =J13*N13 -> 29237.6 | L13: 2024-09 | M13: Q3 | N13: =IF(Table_RawData[[#This Row],[Product_Category]]=$T$8,$U$8,IF(Table_RawData[[#This Row],[Product_Category]]=$T$9,$U$9,IF(Table_RawData[[#This Row],[Product_Category]]=$T$10,$U$10,IF(Table_RawData[[#This Row],[Product_Category]]=$T$11,$U$11,IF(Table_RawData[[#This Row],[Product_Category]]=$T$12,$U$12,"WRONG"))))) -> 0.2
A14: 10013 | B14: 45646 | C14: Fujairah | D14: Ayesha | E14: Deposits | F14: Savings Account | G14: 3 | H14: 5804 | I14: 0.02 | J14: 17412 | K14: =J14*N14 -> 1741.2 | L14: 2024-12 | M14: Q4 | N14: =IF(Table_RawData[[#This Row],[Product_Category]]=$T$8,$U$8,IF(Table_RawData[[#This Row],[Product_Category]]=$T$9,$U$9,IF(Table_RawData[[#This Row],[Product_Category]]=$T$10,$U$10,IF(Table_RawData[[#This Row],[Product_Category]]=$T$11,$U$11,IF(Table_RawData[[#This Row],[Product_Category]]=$T$12,$U$12,"WRONG"))))) -> 0.1
A15: 10014 | B15: 45387 | C15: Dubai | D15: Fatima | E15: Credit Cards | F15: Visa Gold | G15: 7 | H15: 2015 | I15: 0 | J15: 14105 | K15: =J15*N15 -> 4231.5 | L15: 2024-04 | M15: Q2 | N15: =IF(Table_RawData[[#This Row],[Product_Category]]=$T$8,$U$8,IF(Table_RawData[[#This Row],[Product_Category]]=$T$9,$U$9,IF(Table_RawData[[#This Row],[Product_Category]]=$T$10,$U$10,IF(Table_RawData[[#This Row],[Product_Category]]=$T$11,$U$11,IF(Table_RawData[[#This Row],[Product_Category]]=$T$12,$U$12,"WRONG"))))) -> 0.3
A16: 10015 | B16: 45345 | C16: Abu Dhabi | D16: Fatima | E16: Credit Cards | F16: MasterCard Platinum | G16: 9 | H16: 21309 | I16: 0.02 | J16: 191781 | K16: =J16*N16 -> 57534.3 | L16: 2024-02 | M16: Q1 | N16: =IF(Table_RawData[[#This Row],[Product_Category]]=$T$8,$U$8,IF(Table_RawData[[#This Row],[Product_Category]]=$T$9,$U$9,IF(Table_RawData[[#This Row],[Product_Category]]=$T$10,$U$10,IF(Table_RawData[[#This Row],[Product_Category]]=$T$11,$U$11,IF(Table_RawData[[#This Row],[Product_Category]]=$T$12,$U$12,"WRONG"))))) -> 0.3
A17: 10016 | B17: 45640 | C17: Abu Dhabi | D17: Ravi | E17: Retail Loans | F17: Personal Loan | G17: 1 | H17: 1404 | I17: 0.05 | J17: 1404 | K17: =J17*N17 -> 280.8 | L17: 2024-12 | M17: Q4 | N17: =IF(Table_RawData[[#This Row],[Product_Category]]=$T$8,$U$8,IF(Table_RawData[[#This Row],[Product_Category]]=$T$9,$U$9,IF(Table_RawData[[#This Row],[Product_Category]]=$T$10,$U$10,IF(Table_RawData[[#This Row],[Product_Category]]=$T$11,$U$11,IF(Table_RawData[[#This Row],[Product_Category]]=$T$12,$U$12,"WRONG"))))) -> 0.2
A18: 10017 | B18: 45576 | C18: Ajman | D18: Fatima | E18: Wealth | F18: Mutual Funds | G18: 6 | H18: 16106 | I18: 0 | J18: 96636 | K18: =J18*N18 -> 33822.6 | L18: 2024-10 | M18: Q4 | N18: =IF(Table_RawData[[#This Row],[Product_Category]]=$T$8,$U$8,IF(Table_RawData[[#This Row],[Product_Category]]=$T$9,$U$9,IF(Table_RawData[[#This Row],[Product_Category]]=$T$10,$U$10,IF(Table_RawData[[#This Row],[Product_Category]]=$T$11,$U$11,IF(Table_RawData[[#This Row],[Product_Category]]=$T$12,$U$12,"WRONG"))))) -> 0.35
A19: 10018 | B19: 45633 | C19: Dubai | D19: Ravi | E19: SME Banking | F19: Trade Finance | G19: 1 | H19: 49212 | I19: 0.01 | J19: 49212 | K19: =J19*N19 -> 12303 | L19: 2024-12 | M19: Q4 | N19: =IF(Table_RawData[[#This Row],[Product_Category]]=$T$8,$U$8,IF(Table_RawData[[#This Row],[Product_Category]]=$T$9,$U$9,IF(Table_RawData[[#This Row],[Product_Category]]=$T$10,$U$10,IF(Table_RawData[[#This Row],[Product_Category]]=$T$11,$U$11,IF(Table_RawData[[#This Row],[Product_Category]]=$T$12,$U$12,"WRONG"))))) -> 0.25
A20: 10019 | B20: 45394 | C20: Ajman | D20: Leena | E20: Deposits | F20: Savings Account | G20: 1 | H20: 38744 | I20: 0.05 | J20: 38744 | K20: =J20*N20 -> 3874.4 | L20: 2024-04 | M20: Q2 | N20: =IF(Table_RawData[[#This Row],[Product_Category]]=$T$8,$U$8,IF(Table_RawData[[#This Row],[Product_Category]]=$T$9,$U$9,IF(Table_RawData[[#This Row],[Product_Category]]=$T$10,$U$10,IF(Table_RawData[[#This Row],[Product_Category]]=$T$11,$U$11,IF(Table_RawData[[#This Row],[Product_Category]]=$T$12,$U$12,"WRONG"))))) -> 0.1
A21: 10020 | B21: 45562 | C21: Dubai | D21: Karan | E21: Wealth | F21: Bancassurance | G21: 2 | H21: 44125 | I21: 0.02 | J21: 88250 | K21: =J21*N21 -> 30887.5 | L21: 2024-09 | M21: Q3 | N21: =IF(Table_RawData[[#This Row],[Product_Category]]=$T$8,$U$8,IF(Table_RawData[[#This Row],[Product_Category]]=$T$9,$U$9,IF(Table_RawData[[#This Row],[Product_Category]]=$T$10,$U$10,IF(Table_RawData[[#This Row],[Product_Category]]=$T$11,$U$11,IF(Table_RawData[[#This Row],[Product_Category]]=$T$12,$U$12,"WRONG"))))) -> 0.35
A22: 10021 | B22: 45324 | C22: Fujairah | D22: Fatima | E22: Wealth | F22: Mutual Funds | G22: 9 | H22: 23928 | I22: 0.05 | J22: 215352 | K22: =J22*N22 -> 75373.2 | L22: 2024-02 | M22: Q1 | N22: =IF(Table_RawData[[#This Row],[Product_Category]]=$T$8,$U$8,IF(Table_RawData[[#This Row],[Product_Category]]=$T$9,$U$9,IF(Table_RawData[[#This Row],[Product_Category]]=$T$10,$U$10,IF(Table_RawData[[#This Row],[Product_Category]]=$T$11,$U$11,IF(Table_RawData[[#This Row],[Product_Category]]=$T$12,$U$12,"WRONG"))))) -> 0.35
A23: 10022 | B23: 45426 | C23: Fujairah | D23: Ayesha | E23: SME Banking | F23: Working Capital | G23: 3 | H23: 16781 | I23: 0.05 | J23: 50343 | K23: =J23*N23 -> 12585.75 | L23: 2024-05 | M23: Q2 | N23: =IF(Table_RawData[[#This Row],[Product_Category]]=$T$8,$U$8,IF(Table_RawData[[#This Row],[Product_Category]]=$T$9,$U$9,IF(Table_RawData[[#This Row],[Product_Category]]=$T$10,$U$10,IF(Table_RawData[[#This Row],[Product_Category]]=$T$11,$U$11,IF(Table_RawData[[#This Row],[Product_Category]]=$T$12,$U$12,"WRONG"))))) -> 0.25
A24: 10023 | B24: 45324 | C24: Fujairah | D24: Ravi | E24: Credit Cards | F24: Visa Gold | G24: 2 | H24: 18715 | I24: 0 | J24: 37430 | K24: =J24*N24 -> 11229 | L24: 2024-02 | M24: Q1 | N24: =IF(Table_RawData[[#This Row],[Product_Category]]=$T$8,$U$8,IF(Table_RawData[[#This Row],[Product_Category]]=$T$9,$U$9,IF(Table_RawData[[#This Row],[Product_Category]]=$T$10,$U$10,IF(Table_RawData[[#This Row],[Product_Category]]=$T$11,$U$11,IF(Table_RawData[[#This Row],[Product_Category]]=$T$12,$U$12,"WRONG"))))) -> 0.3
... A601: 10600 | B601: 45598 | C601: Dubai | D601: Ravi | E601: Deposits | F601: Fixed Deposit | G601: 7 | H601: 34066 | I601: 0 | J601: 238462 | K601: =J601*N601 -> 23846.2 | L601: 2024-11 | M601: Q4 | N601: =IF(Table_RawData[[#This Row],[Product_Category]]=$T$8,$U$8,IF(Table_RawData[[#This Row],[Product_Category]]=$T$9,$U$9,IF(Table_RawData[[#This Row],[Product_Category]]=$T$10,$U$10,IF(Table_RawData[[#This Row],[Product_Category]]=$T$11,$U$11,IF(Table_RawData[[#This Row],[Product_Category]]=$T$12,$U$12,"WRONG"))))) -> 0.1

Sheet Summary
A1: Summary: Region x Month Revenue
A3: Region/Month | B3: 2024-01 | C3: 2024-02 | D3: 2024-03 | E3: 2024-04 | F3: 2024-05 | G3: 2024-06 | H3: 2024-07 | I3: 2024-08 | J3: 2024-09 | K3: 2024-10 | L3: 2024-11 | M3: 2024-12
A4: Dubai | B4: =SUMIFS(Raw_Data!$J:$J,Raw_Data!$C:$C,"Dubai",Raw_Data!$L:$L,"2024-01") -> 953430 | C4: =SUMIFS(Raw_Data!$J:$J,Raw_Data!$C:$C,"Dubai",Raw_Data!$L:$L,"2024-02") -> 355306 | D4: =SUMIFS(Raw_Data!$J:$J,Raw_Data!$C:$C,"Dubai",Raw_Data!$L:$L,"2024-03") -> 347818 | E4: =SUMIFS(Raw_Data!$J:$J,Raw_Data!$C:$C,"Dubai",Raw_Data!$L:$L,"2024-04") -> 1979616 | F4: =SUMIFS(Raw_Data!$J:$J,Raw_Data!$C:$C,"Dubai",Raw_Data!$L:$L,"2024-05") -> 1390819 | G4: =SUMIFS(Raw_Data!$J:$J,Raw_Data!$C:$C,"Dubai",Raw_Data!$L:$L,"2024-06") -> 697472 | H4: =SUMIFS(Raw_Data!$J:$J,Raw_Data!$C:$C,"Dubai",Raw_Data!$L:$L,"2024-07") -> 1197787 | I4: =SUMIFS(Raw_Data!$J:$J,Raw_Data!$C:$C,"Dubai",Raw_Data!$L:$L,"2024-08") -> 1746772 | J4: =SUMIFS(Raw_Data!$J:$J,Raw_Data!$C:$C,"Dubai",Raw_Data!$L:$L,"2024-09") -> 1237811 | K4: =SUMIFS(Raw_Data!$J:$J,Raw_Data!$C:$C,"Dubai",Raw_Data!$L:$L,"2024-10") -> 175025 | L4: =SUMIFS(Raw_Data!$J:$J,Raw_Data!$C:$C,"Dubai",Raw_Data!$L:$L,"2024-11") -> 866105 | M4: =SUMIFS(Raw_Data!$J:$J,Raw_Data!$C:$C,"Dubai",Raw_Data!$L:$L,"2024-12") -> 1079863
A5: Abu Dhabi | B5: =SUMIFS(Raw_Data!$J:$J,Raw_Data!$C:$C,"Abu Dhabi",Raw_Data!$L:$L,"2024-01") -> 912062 | C5: =SUMIFS(Raw_Data!$J:$J,Raw_Data!$C:$C,"Abu Dhabi",Raw_Data!$L:$L,"2024-02") -> 1996051 | D5: =SUMIFS(Raw_Data!$J:$J,Raw_Data!$C:$C,"Abu Dhabi",Raw_Data!$L:$L,"2024-03") -> 1074668 | E5: =SUMIFS(Raw_Data!$J:$J,Raw_Data!$C:$C,"Abu Dhabi",Raw_Data!$L:$L,"2024-04") -> 1997470 | F5: =SUMIFS(Raw_Data!$J:$J,Raw_Data!$C:$C,"Abu Dhabi",Raw_Data!$L:$L,"2024-05") -> 2903086 | G5: =SUMIFS(Raw_Data!$J:$J,Raw_Data!$C:$C,"Abu Dhabi",Raw_Data!$L:$L,"2024-06") -> 483073 | H5: =SUMIFS(Raw_Data!$J:$J,Raw_Data!$C:$C,"Abu Dhabi",Raw_Data!$L:$L,"2024-07") -> 1193974 | I5: =SUMIFS(Raw_Data!$J:$J,Raw_Data!$C:$C,"Abu Dhabi",Raw_Data!$L:$L,"2024-08") -> 294312 | J5: =SUMIFS(Raw_Data!$J:$J,Raw_Data!$C:$C,"Abu Dhabi",Raw_Data!$L:$L,"2024-09") -> 943495 | K5: =SUMIFS(Raw_Data!$J:$J,Raw_Data!$C:$C,"Abu Dhabi",Raw_Data!$L:$L,"2024-10") -> 1338977 | L5: =SUMIFS(Raw_Data!$J:$J,Raw_Data!$C:$C,"Abu Dhabi",Raw_Data!$L:$L,"2024-11") -> 1359266 | M5: =SUMIFS(Raw_Data!$J:$J,Raw_Data!$C:$C,"Abu Dhabi",Raw_Data!$L:$L,"2024-12") -> 1176568
A6: Ras Al Khaimah | B6: =SUMIFS(Raw_Data!$J:$J,Raw_Data!$C:$C,"Ras Al Khaimah",Raw_Data!$L:$L,"2024-01") -> 1178841 | C6: =SUMIFS(Raw_Data!$J:$J,Raw_Data!$C:$C,"Ras Al Khaimah",Raw_Data!$L:$L,"2024-02") -> 1090738 | D6: =SUMIFS(Raw_Data!$J:$J,Raw_Data!$C:$C,"Ras Al Khaimah",Raw_Data!$L:$L,"2024-03") -> 914305 | E6: =SUMIFS(Raw_Data!$J:$J,Raw_Data!$C:$C,"Ras Al Khaimah",Raw_Data!$L:$L,"2024-04") -> 614478 | F6: =SUMIFS(Raw_Data!$J:$J,Raw_Data!$C:$C,"Ras Al Khaimah",Raw_Data!$L:$L,"2024-05") -> 1306157 | G6: =SUMIFS(Raw_Data!$J:$J,Raw_Data!$C:$C,"Ras Al Khaimah",Raw_Data!$L:$L,"2024-06") -> 428736 | H6: =SUMIFS(Raw_Data!$J:$J,Raw_Data!$C:$C,"Ras Al Khaimah",Raw_Data!$L:$L,"2024-07") -> 883121 | I6: =SUMIFS(Raw_Data!$J:$J,Raw_Data!$C:$C,"Ras Al Khaimah",Raw_Data!$L:$L,"2024-08") -> 1800438 | J6: =SUMIFS(Raw_Data!$J:$J,Raw_Data!$C:$C,"Ras Al Khaimah",Raw_Data!$L:$L,"2024-09") -> 1377391 | K6: =SUMIFS(Raw_Data!$J:$J,Raw_Data!$C:$C,"Ras Al Khaimah",Raw_Data!$L:$L,"2024-10") -> 2224518 | L6: =SUMIFS(Raw_Data!$J:$J,Raw_Data!$C:$C,"Ras Al Khaimah",Raw_Data!$L:$L,"2024-11") -> 1187676 | M6: =SUMIFS(Raw_Data!$J:$J,Raw_Data!$C:$C,"Ras Al Khaimah",Raw_Data!$L:$L,"2024-12") -> 1525026
A7: Ajman | B7: =SUMIFS(Raw_Data!$J:$J,Raw_Data!$C:$C,"Ajman",Raw_Data!$L:$L,"2024-01") -> 791649 | C7: =SUMIFS(Raw_Data!$J:$J,Raw_Data!$C:$C,"Ajman",Raw_Data!$L:$L,"2024-02") -> 2020920 | D7: =SUMIFS(Raw_Data!$J:$J,Raw_Data!$C:$C,"Ajman",Raw_Data!$L:$L,"2024-03") -> 492128 | E7: =SUMIFS(Raw_Data!$J:$J,Raw_Data!$C:$C,"Ajman",Raw_Data!$L:$L,"2024-04") -> 1083070 | F7: =SUMIFS(Raw_Data!$J:$J,Raw_Data!$C:$C,"Ajman",Raw_Data!$L:$L,"2024-05") -> 1333662 | G7: =SUMIFS(Raw_Data!$J:$J,Raw_Data!$C:$C,"Ajman",Raw_Data!$L:$L,"2024-06") -> 877652 | H7: =SUMIFS(Raw_Data!$J:$J,Raw_Data!$C:$C,"Ajman",Raw_Data!$L:$L,"2024-07") -> 247422 | I7: =SUMIFS(Raw_Data!$J:$J,Raw_Data!$C:$C,"Ajman",Raw_Data!$L:$L,"2024-08") -> 1267343 | J7: =SUMIFS(Raw_Data!$J:$J,Raw_Data!$C:$C,"Ajman",Raw_Data!$L:$L,"2024-09") -> 513816 | K7: =SUMIFS(Raw_Data!$J:$J,Raw_Data!$C:$C,"Ajman",Raw_Data!$L:$L,"2024-10") -> 535667 | L7: =SUMIFS(Raw_Data!$J:$J,Raw_Data!$C:$C,"Ajman",Raw_Data!$L:$L,"2024-11") -> 248682 | M7: =SUMIFS(Raw_Data!$J:$J,Raw_Data!$C:$C,"Ajman",Raw_Data!$L:$L,"2024-12") -> 1027553
A8: Sharjah | B8: =SUMIFS(Raw_Data!$J:$J,Raw_Data!$C:$C,"Sharjah",Raw_Data!$L:$L,"2024-01") -> 569009 | C8: =SUMIFS(Raw_Data!$J:$J,Raw_Data!$C:$C,"Sharjah",Raw_Data!$L:$L,"2024-02") -> 1578948 | D8: =SUMIFS(Raw_Data!$J:$J,Raw_Data!$C:$C,"Sharjah",Raw_Data!$L:$L,"2024-03") -> 990741 | E8: =SUMIFS(Raw_Data!$J:$J,Raw_Data!$C:$C,"Sharjah",Raw_Data!$L:$L,"2024-04") -> 736219 | F8: =SUMIFS(Raw_Data!$J:$J,Raw_Data!$C:$C,"Sharjah",Raw_Data!$L:$L,"2024-05") -> 1773463 | G8: =SUMIFS(Raw_Data!$J:$J,Raw_Data!$C:$C,"Sharjah",Raw_Data!$L:$L,"2024-06") -> 1569994 | H8: =SUMIFS(Raw_Data!$J:$J,Raw_Data!$C:$C,"Sharjah",Raw_Data!$L:$L,"2024-07") -> 1454965 | I8: =SUMIFS(Raw_Data!$J:$J,Raw_Data!$C:$C,"Sharjah",Raw_Data!$L:$L,"2024-08") -> 1225421 | J8: =SUMIFS(Raw_Data!$J:$J,Raw_Data!$C:$C,"Sharjah",Raw_Data!$L:$L,"2024-09") -> 670259 | K8: =SUMIFS(Raw_Data!$J:$J,Raw_Data!$C:$C,"Sharjah",Raw_Data!$L:$L,"2024-10") -> 704780 | L8: =SUMIFS(Raw_Data!$J:$J,Raw_Data!$C:$C,"Sharjah",Raw_Data!$L:$L,"2024-11") -> 1208821 | M8: =SUMIFS(Raw_Data!$J:$J,Raw_Data!$C:$C,"Sharjah",Raw_Data!$L:$L,"2024-12") -> 982387
A9: Fujairah | B9: =SUMIFS(Raw_Data!$J:$J,Raw_Data!$C:$C,"Fujairah",Raw_Data!$L:$L,"2024-01") -> 1141670 | C9: =SUMIFS(Raw_Data!$J:$J,Raw_Data!$C:$C,"Fujairah",Raw_Data!$L:$L,"2024-02") -> 1125958 | D9: =SUMIFS(Raw_Data!$J:$J,Raw_Data!$C:$C,"Fujairah",Raw_Data!$L:$L,"2024-03") -> 504455 | E9: =SUMIFS(Raw_Data!$J:$J,Raw_Data!$C:$C,"Fujairah",Raw_Data!$L:$L,"2024-04") -> 988033 | F9: =SUMIFS(Raw_Data!$J:$J,Raw_Data!$C:$C,"Fujairah",Raw_Data!$L:$L,"2024-05") -> 901049 | G9: =SUMIFS(Raw_Data!$J:$J,Raw_Data!$C:$C,"Fujairah",Raw_Data!$L:$L,"2024-06") -> 1090427 | H9: =SUMIFS(Raw_Data!$J:$J,Raw_Data!$C:$C,"Fujairah",Raw_Data!$L:$L,"2024-07") -> 913417 | I9: =SUMIFS(Raw_Data!$J:$J,Raw_Data!$C:$C,"Fujairah",Raw_Data!$L:$L,"2024-08") -> 712144 | J9: =SUMIFS(Raw_Data!$J:$J,Raw_Data!$C:$C,"Fujairah",Raw_Data!$L:$L,"2024-09") -> 890883 | K9: =SUMIFS(Raw_Data!$J:$J,Raw_Data!$C:$C,"Fujairah",Raw_Data!$L:$L,"2024-10") -> 805158 | L9: =SUMIFS(Raw_Data!$J:$J,Raw_Data!$C:$C,"Fujairah",Raw_Data!$L:$L,"2024-11") -> 297885 | M9: =SUMIFS(Raw_Data!$J:$J,Raw_Data!$C:$C,"Fujairah",Raw_Data!$L:$L,"2024-12") -> 568969
A11: TOTAL | B11: =SUM(B4:B9) -> 5546661 | C11: =SUM(C4:C9) -> 8167921 | D11: =SUM(D4:D9) -> 4324115 | E11: =SUM(E4:E9) -> 7398886 | F11: =SUM(F4:F9) -> 9608236 | G11: =SUM(G4:G9) -> 5147354 | H11: =SUM(H4:H9) -> 5890686 | I11: =SUM(I4:I9) -> 7046430 | ... M11: =SUM(M4:M9) -> 6360366

Sheet Top_Reps
A1: Top Sales Representatives (Total Revenue) | B1: Column1
A2: Sales_Rep | B2: Total_Revenue
A3: Zain | B3: =SUMIFS(Raw_Data!$J:$J,Raw_Data!$D:$D,"Zain") -> 8092627
A4: Ayesha | B4: =SUMIFS(Raw_Data!$J:$J,Raw_Data!$D:$D,"Ayesha") -> 5584113
A5: Ravi | B5: =SUMIFS(Raw_Data!$J:$J,Raw_Data!$D:$D,"Ravi") -> 7649148
A6: Leena | B6: =SUMIFS(Raw_Data!$J:$J,Raw_Data!$D:$D,"Leena") -> 7084240
A7: Fatima | B7: =SUMIFS(Raw_Data!$J:$J,Raw_Data!$D:$D,"Fatima") -> 10688171
A8: Omar | B8: =SUMIFS(Raw_Data!$J:$J,Raw_Data!$D:$D,"Omar") -> 7032470
A9: Sara | B9: =SUMIFS(Raw_Data!$J:$J,Raw_Data!$D:$D,"Sara") -> 7575855
A10: Mohan | B10: =SUMIFS(Raw_Data!$J:$J,Raw_Data!$D:$D,"Mohan") -> 6794121
A11: Priyanka | B11: =SUMIFS(Raw_Data!$J:$J,Raw_Data!$D:$D,"Priyanka") -> 10149153
A12: Karan | B12: =SUMIFS(Raw_Data!$J:$J,Raw_Data!$D:$D,"Karan") -> 5426972

Sheet Dashboard
A1: Banking Analytics - Sales Dashboard
A3: Total Revenue | B3: =SUM(Raw_Data!J:J) -> 76076870
A4: Total Profit | B4: =SUM(Raw_Data!K:K) -> 18527489
A5: Average Profit Margin | B5: =AVERAGE(Raw_Data!K:K)/AVERAGE(Raw_Data!J:J) -> 0.24353642
A6: Top Region | B6: =INDEX(O9:O14,MATCH(MAX(P9:P14),P9:P14,0)) -> Abu Dhabi
O8: Helper Regions
O9: Dubai | P9: =SUM(Summary!B4:M4) -> 12027824
O10: Abu Dhabi | P10: =SUM(Summary!B5:M5) -> 15673002
O11: Ras Al Khaimah | P11: =SUM(Summary!B6:M6) -> 14531425
O12: Ajman | P12: =SUM(Summary!B7:M7) -> 10439564
O13: Sharjah | P13: =SUM(Summary!B8:M8) -> 13465007
O14: Fujairah | P14: =SUM(Summary!B9:M9) -> 9940048
A20: Region | B20: Total_Revenue | F20: Month | G20: Month_Revenue
A21: Dubai | B21: =SUMIFS(Raw_Data!$J:$J,Raw_Data!$C:$C,"Dubai") -> 12027824 | F21: 2024-01 | G21: =SUMIFS(Raw_Data!$J:$J,Raw_Data!$L:$L,"2024-01") -> 5546661
A22: Abu Dhabi | B22: =SUMIFS(Raw_Data!$J:$J,Raw_Data!$C:$C,"Abu Dhabi") -> 15673002 | F22: 2024-02 | G22: =SUMIFS(Raw_Data!$J:$J,Raw_Data!$L:$L,"2024-02") -> 8167921
A23: Ras Al Khaimah | B23: =SUMIFS(Raw_Data!$J:$J,Raw_Data!$C:$C,"Ras Al Khaimah") -> 14531425 | F23: 2024-03 | G23: =SUMIFS(Raw_Data!$J:$J,Raw_Data!$L:$L,"2024-03") -> 4324115
A24: Ajman | B24: =SUMIFS(Raw_Data!$J:$J,Raw_Data!$C:$C,"Ajman") -> 10439564 | F24: 2024-04 | G24: =SUMIFS(Raw_Data!$J:$J,Raw_Data!$L:$L,"2024-04") -> 7398886
A25: Sharjah | B25: =SUMIFS(Raw_Data!$J:$J,Raw_Data!$C:$C,"Sharjah") -> 13465007 | F25: 2024-05 | G25: =SUMIFS(Raw_Data!$J:$J,Raw_Data!$L:$L,"2024-05") -> 9608236
A26: Fujairah | B26: =SUMIFS(Raw_Data!$J:$J,Raw_Data!$C:$C,"Fujairah") -> 9940048 | F26: 2024-06 | G26: =SUMIFS(Raw_Data!$J:$J,Raw_Data!$L:$L,"2024-06") -> 5147354
F27: 2024-07 | G27: =SUMIFS(Raw_Data!$J:$J,Raw_Data!$L:$L,"2024-07") -> 5890686
F28: 2024-08 | G28: =SUMIFS(Raw_Data!$J:$J,Raw_Data!$L:$L,"2024-08") -> 7046430
F29: 2024-09 | G29: =SUMIFS(Raw_Data!$J:$J,Raw_Data!$L:$L,"2024-09") -> 5633655
F30: 2024-10 | G30: =SUMIFS(Raw_Data!$J:$J,Raw_Data!$L:$L,"2024-10") -> 5784125
F31: 2024-11 | G31: =SUMIFS(Raw_Data!$J:$J,Raw_Data!$L:$L,"2024-11") -> 5168435
F32: 2024-12 | G32: =SUMIFS(Raw_Data!$J:$J,Raw_Data!$L:$L,"2024-12") -> 6360366
